var tent4 = {
"type": "FeatureCollection",
"crs": { "type": "name", "properties": { "name": "urn:ogc:def:crs:OGC:1.3:CRS84" } },

"features": [
{ "type": "Feature", "properties": { "lat": 139.958351, "lng": 35.801702, "icon": "img\/tent.png", "popup": "4丁目テント" }, "geometry": { "type": "Point", "coordinates": [ 139.958351, 35.801702 ] } },
]
}