var tyuou ={
"type": "FeatureCollection",
"crs": { "type": "name", "properties": { "name": "urn:ogc:def:crs:OGC:1.3:CRS84" } },

"features": [
{ "type": "Feature", "properties": { "lat": 139.950930, "lng": 35.802193, "icon": "img\/tyuou.png", "popup": "中央ステージ" }, "geometry": { "type": "Point", "coordinates": [ 139.9509304, 35.80219307 ] } }
]
}
